Metadata-Version: 1.1
Name: HAL-9000
Version: 4.0.0
Summary: A Deep Learning framework
Home-page: UNKNOWN
Author: Harin Kumar
Author-email: Harinkumar851@gmail.com
License: MIT
Keywords: neuralnetworks
Platform: UNKNOWN
Classifier: Development Status :: 5 - Production/Stable
Classifier: Intended Audience :: Education
Classifier: Operating System :: Microsoft :: Windows :: Windows 10
Classifier: License :: OSI Approved :: MIT License
Classifier: Programming Language :: Python :: 3
